django_pylibmc_threadsafe.py
django_pylibmc_threadsafe-1.0.1.dist-info/LICENSE
django_pylibmc_threadsafe-1.0.1.dist-info/METADATA
django_pylibmc_threadsafe-1.0.1.dist-info/WHEEL
django_pylibmc_threadsafe-1.0.1.dist-info/top_level.txt
django_pylibmc_threadsafe-1.0.1.dist-info/RECORD
