Metadata-Version: 2.1
Name: django-pylibmc-threadsafe
Version: 1.0.1
Summary: Thread safe pylibmc cache pbackend for django
Author-email: Miroslav Bendík <miroslav.bendik@gmail.com>
License: MIT
Project-URL: homepage, https://github.com/mireq/django-pylibmc-threadsafe
Project-URL: documentation, https://github.com/mireq/django-pylibmc-threadsafe
Project-URL: repository, https://github.com/mireq/django-pylibmc-threadsafe
Project-URL: changelog, https://github.com/mireq/django-pylibmc-threadsafe/blob/master/CHANGELOG.md
Keywords: pylibmc,django
Classifier: Programming Language :: Python :: 3
Requires-Python: >=3.7
License-File: LICENSE
Requires-Dist: django
Requires-Dist: pylibmc
Provides-Extra: dev
Requires-Dist: pylint ; extra == 'dev'
Requires-Dist: pre-commit ; extra == 'dev'
Requires-Dist: bump2version ; extra == 'dev'
Requires-Dist: commitizen ; extra == 'dev'
